ppping/__init__.py
ppping/__version__.py
ppping/line.py
ppping/parser.py
ppping/ppping.py
ppping/script.py
ppping-0.1.10.dist-info/LICENSE
ppping-0.1.10.dist-info/METADATA
ppping-0.1.10.dist-info/WHEEL
ppping-0.1.10.dist-info/entry_points.txt
ppping-0.1.10.dist-info/top_level.txt
ppping-0.1.10.dist-info/RECORD
