Metadata-Version: 2.1
Name: ppping
Version: 0.1.10
Summary: ping monitoring tool written in Python
Home-page: http://github.com/johejo/ppping
Author: Mitsuo Heijo
Author-email: mitsuo_h@outlook.com
License: MIT
Platform: Linux
Platform: UNIX
Platform: macOS
Classifier: Development Status :: 4 - Beta
Classifier: Environment :: Console :: Curses
Classifier: Intended Audience :: Developers
Classifier: License :: OSI Approved :: MIT License
Classifier: Operating System :: MacOS :: MacOS X
Classifier: Operating System :: POSIX
Classifier: Programming Language :: Python :: 3 :: Only
Classifier: Programming Language :: Python :: 3.6
Classifier: Programming Language :: Python :: 3.7
Classifier: Topic :: System :: Networking :: Monitoring
Requires-Python: >=3.5
